django_weed2-0.2.4.dist-info/METADATA
django_weed2-0.2.4.dist-info/RECORD
django_weed2-0.2.4.dist-info/WHEEL
django_weed2-0.2.4.dist-info/top_level.txt
djweed/__init__.py
djweed/db_fields.py
djweed/storage.py
djweed/urls.py
djweed/version.py
djweed/views.py
