Metadata-Version: 2.1
Name: django-weed2
Version: 0.2.4
Summary: Weed-FS integration into Django as a storage
Home-page: https://github.com/waipbmtd/django-weed
Author: Devin
Author-email: waipbmtd@gmail.com
License: MIT
Platform: UNKNOWN
Requires-Dist: django
Requires-Dist: pyseaweed (>=0.3.3)
Requires-Dist: six
